radikoplaylist/__init__.py
radikoplaylist/authorization.py
radikoplaylist/exceptions.py
radikoplaylist/master_playlist.py
radikoplaylist/master_playlist_client.py
radikoplaylist/master_playlist_request.py
radikoplaylist/playlist_create_url_getter.py
radikoplaylist/py.typed
radikoplaylist/requester.py
radikoplaylist-1.2.0.dist-info/licenses/LICENSE
radikoplaylist-1.2.0.dist-info/METADATA
radikoplaylist-1.2.0.dist-info/WHEEL
radikoplaylist-1.2.0.dist-info/top_level.txt
radikoplaylist-1.2.0.dist-info/RECORD
