Metadata-Version: 2.4
Name: radikoplaylist
Version: 1.2.0
Summary: Accesses to radiko API, gets media playlist URL and built header for HTTP request to its URL.
Author-email: Master <roadmasternavi@gmail.com>
Maintainer-email: Master <roadmasternavi@gmail.com>
License: MIT License
Project-URL: homepage, https://github.com/road-master/radiko-playlist
Project-URL: repository, https://github.com/road-master/radiko-playlist
Keywords: radikoplaylist
Classifier: Development Status :: 5 - Production/Stable
Classifier: Intended Audience :: Developers
Classifier: Natural Language :: English
Classifier: Operating System :: OS Independent
Classifier: Topic :: Software Development
Classifier: Topic :: Software Development :: Libraries
Classifier: Topic :: Software Development :: Build Tools
Classifier: Topic :: Software Development :: Libraries :: Python Modules
Classifier: Programming Language :: Python
Classifier: Programming Language :: Python :: 3
Classifier: Programming Language :: Python :: 3.7
Classifier: Programming Language :: Python :: 3.8
Classifier: Programming Language :: Python :: 3.9
Classifier: Programming Language :: Python :: 3.10
Classifier: Programming Language :: Python :: 3.11
Classifier: Programming Language :: Python :: 3.12
Classifier: Programming Language :: Python :: 3.13
Classifier: Topic :: Internet
Classifier: Topic :: Internet :: WWW/HTTP
Classifier: Typing :: Typed
Requires-Python: >=3.7
License-File: LICENSE
Requires-Dist: defusedxml
Requires-Dist: m3u8
Requires-Dist: requests
Dynamic: license-file
